gncxml/__init__.py
gncxml/__main__.py
gncxml/_cli.py
gncxml/_iso4217.py
gncxml/book.py
gncxml-0.7.16.dist-info/METADATA
gncxml-0.7.16.dist-info/WHEEL
gncxml-0.7.16.dist-info/entry_points.txt
gncxml-0.7.16.dist-info/licenses/LICENSE
gncxml-0.7.16.dist-info/RECORD
