Metadata-Version: 2.4
Name: gncxml
Version: 0.7.16
Summary: Extract entries from GnuCash data file to pandas.DataFrame.
License: Apache-2.0
License-File: LICENSE
Author: LiosK
Author-email: contact@mail.liosk.net
Requires-Python: >=3.10
Classifier: License :: OSI Approved :: Apache Software License
Classifier: Operating System :: OS Independent
Classifier: Programming Language :: Python :: 3
Classifier: Programming Language :: Python :: 3.10
Classifier: Programming Language :: Python :: 3.11
Classifier: Programming Language :: Python :: 3.12
Classifier: Programming Language :: Python :: 3.13
Classifier: Programming Language :: Python :: 3.14
Classifier: Topic :: Office/Business :: Financial
Requires-Dist: pandas (>=2.2)
Project-URL: Homepage, https://github.com/LiosK/gncxml
